cepy/__init__.py
cepy/ce.py
cepy/embed_align.py
cepy/parallel.py
cepy/utils.py
cepy/data/ce_group.json.gz
cepy/data/ce_subject1.json
cepy/data/ce_subject1.json.gz
cepy/data/ce_subject2.json.gz
cepy/data/sc_group_matrix.npz
cepy/data/sc_subject1_matrix.npz
cepy/data/sc_subject2_matrix.npz
cepy/data/__pycache__/generate_example_ce.cpython-37.pyc
cepy-1.0.0.dist-info/LICENSE
cepy-1.0.0.dist-info/METADATA
cepy-1.0.0.dist-info/WHEEL
cepy-1.0.0.dist-info/top_level.txt
cepy-1.0.0.dist-info/RECORD
