Metadata-Version: 2.1
Name: cepy
Version: 1.0.0
Summary: Implementation of the connectome embedding workflow.
Home-page: https://github.com/gidlev/cepy
Author: Gidon Levakov
Author-email: gidonlevakov@gmail.com
License: UNKNOWN
Platform: UNKNOWN
Classifier: Programming Language :: Python :: 3
Classifier: License :: OSI Approved :: MIT License
Classifier: Operating System :: OS Independent
Requires-Python: >=3.5
Requires-Dist: networkx
Requires-Dist: gensim
Requires-Dist: numpy
Requires-Dist: tqdm
Requires-Dist: joblib (>=0.13.2)
